{
    "test_file_path": "data/traj_3d_body_pose_220/035",
    "task_1": {
        "period_num": 6,
        "period_boundaries": {
            "0": [
                0,
                822
            ],
            "1": [
                823,
                1533
            ],
            "2": [
                1534,
                2351
            ],
            "3": [
                2352,
                3043
            ],
            "4": [
                3044,
                3847
            ],
            "5": [
                3848,
                4533
            ]
        }
    },
    "task_2": {
        "est_remained_ratio": 0.4840182648401826
    },
    "task_3": {
        "est_abnormal_range": [
            640.0,
            657.0
        ]
    }
}